composition_based_feature_vector/__init__.py
composition_based_feature_vector/composition.py
composition_based_feature_vector/meta.yaml
composition_based_feature_vector/element_properties/jarvis.csv
composition_based_feature_vector/element_properties/magpie.csv
composition_based_feature_vector/element_properties/mat2vec.csv
composition_based_feature_vector/element_properties/oliynyk.csv
composition_based_feature_vector/element_properties/onehot.csv
composition_based_feature_vector/element_properties/random_200.csv
composition_based_feature_vector/tests/test.py
composition_based_feature_vector/tests/test_composition.py
composition_based_feature_vector-1.0.6.dist-info/LICENSE
composition_based_feature_vector-1.0.6.dist-info/WHEEL
composition_based_feature_vector-1.0.6.dist-info/METADATA
composition_based_feature_vector-1.0.6.dist-info/RECORD
