Metadata-Version: 2.1
Name: composition_based_feature_vector
Version: 1.0.6
Summary: Tool for quickly creating a composition-based feature vector.
Author: Andrew Falkowski
Author-email: Steven Kauwe <jkkauwe@gmail.com>, Anthony Wang <aytwang@alumni.uwaterloo.ca>, "Sterling G. Baird" <sterling.baird@utah.edu>
Requires-Python: >=3
Classifier: License :: OSI Approved :: MIT License
Classifier: Development Status :: 3 - Alpha
Classifier: Intended Audience :: Science/Research
Classifier: Operating System :: POSIX :: Linux
Classifier: Operating System :: MacOS
Classifier: Operating System :: Microsoft :: Windows
Classifier: Programming Language :: Python :: 3
Classifier: Programming Language :: Python :: 3.4
Classifier: Programming Language :: Python :: 3.5
Classifier: Programming Language :: Python :: 3.6
Classifier: Programming Language :: Python :: 3.7
Classifier: Programming Language :: Python :: 3.8
Classifier: Programming Language :: Python :: 3.9
Classifier: Programming Language :: Python :: 3.10
Requires-Dist: numpy
Requires-Dist: pandas
Requires-Dist: tqdm
Requires-Dist: pytest
Project-URL: Home, https://github.com/sparks-baird/CBFV
